my_sdk/__init__.py
my_sdk/__main__.py
my_sdk/module1.py
my_sdk/module2.py
my_sdk_cli-0.0.3.dist-info/LICENSE
my_sdk_cli-0.0.3.dist-info/METADATA
my_sdk_cli-0.0.3.dist-info/WHEEL
my_sdk_cli-0.0.3.dist-info/entry_points.txt
my_sdk_cli-0.0.3.dist-info/top_level.txt
my_sdk_cli-0.0.3.dist-info/RECORD
